gcl_iam/__init__.py
gcl_iam/algorithms.py
gcl_iam/constants.py
gcl_iam/contexts.py
gcl_iam/controllers.py
gcl_iam/drivers.py
gcl_iam/enforcers.py
gcl_iam/engines.py
gcl_iam/exceptions.py
gcl_iam/middlewares.py
gcl_iam/opts.py
gcl_iam/rules.py
gcl_iam/tokens.py
gcl_iam/tests/__init__.py
gcl_iam/tests/functional/__init__.py
gcl_iam/tests/functional/clients.py
gcl_iam/tests/functional/test_basic.py
gcl_iam/tests/unit/__init__.py
gcl_iam/tests/unit/test_algorithms.py
gcl_iam/tests/unit/test_basic.py
gcl_iam/tests/unit/test_contexts.py
gcl_iam/tests/unit/test_controllers.py
gcl_iam/tests/unit/test_enforsers.py
gcl_iam-1.0.3.dist-info/licenses/AUTHORS
gcl_iam-1.0.3.dist-info/licenses/LICENSE
gcl_iam-1.0.3.dist-info/METADATA
gcl_iam-1.0.3.dist-info/WHEEL
gcl_iam-1.0.3.dist-info/pbr.json
gcl_iam-1.0.3.dist-info/top_level.txt
gcl_iam-1.0.3.dist-info/RECORD
