Metadata-Version: 2.4
Name: gcl_iam
Version: 1.0.3
Summary: My project summary
Home-page: https://github.com/infraguys/gcl_iam/
Author: Genesis Corporation
Author-email: eugene@frolov.net.ru
Classifier: Intended Audience :: Developers
Classifier: License :: OSI Approved :: Apache Software License
Classifier: Operating System :: POSIX :: Linux
Classifier: Programming Language :: Python
Classifier: Programming Language :: Python :: 3
Classifier: Programming Language :: Python :: 3.8
Classifier: Programming Language :: Python :: 3.10
Classifier: Programming Language :: Python :: 3.11
Classifier: Programming Language :: Python :: 3.12
Classifier: Programming Language :: Python :: 3.13
License-File: LICENSE
License-File: AUTHORS
Requires-Dist: pbr<=5.8.1,>=1.10.0
Requires-Dist: bazooka<2.0.0,>=1.1.0
Requires-Dist: izulu<1.0.0,>=0.50.0
Requires-Dist: pyjwt<3.0.0,>=2.9.0
Requires-Dist: restalchemy<16.0.0,>=14.0.0
Requires-Dist: cryptography<47.0.0,>=45.0.5
Dynamic: author
Dynamic: author-email
Dynamic: classifier
Dynamic: description
Dynamic: home-page
Dynamic: license-file
Dynamic: requires-dist
Dynamic: summary
